pyramid_skins/__init__.py
pyramid_skins/configuration.py
pyramid_skins/configure.zcml
pyramid_skins/discovery.py
pyramid_skins/interfaces.py
pyramid_skins/meta.zcml
pyramid_skins/models.py
pyramid_skins/renderer.py
pyramid_skins/routes.py
pyramid_skins/zcml.py
pyramid_skins/docs/conf.py
pyramid_skins/docs/extending.rst
pyramid_skins/docs/glossary.rst
pyramid_skins/docs/index.rst
pyramid_skins/docs/registration.rst
pyramid_skins/docs/routing.rst
pyramid_skins/docs/templates.rst
pyramid_skins/tests/__init__.py
pyramid_skins/tests/test_doctests.py
pyramid_skins/tests/test_imperative.py
pyramid_skins/tests/test_renderer.py
pyramid_skins/tests/alt_skins/main_template.pt
pyramid_skins/tests/other_skins/main_template.pt
pyramid_skins/tests/skins/index.pt
pyramid_skins/tests/skins/main_template.pt
pyramid_skins/tests/skins/about/index.pt
pyramid_skins/tests/skins/about/images/logo.png
pyramid_skins/tests/skins/images/logo.png
pyramid_skins-3.0.dist-info/METADATA
pyramid_skins-3.0.dist-info/WHEEL
pyramid_skins-3.0.dist-info/namespace_packages.txt
pyramid_skins-3.0.dist-info/top_level.txt
pyramid_skins-3.0.dist-info/RECORD
