Metadata-Version: 2.1
Name: pyramid-skins
Version: 3.0
Summary: Templating framework for Pyramid.
Home-page: http://packages.python.org/pyramid_skins/
Author: Malthe Borch and the Pylons Community
Author-email: pylons-discuss@googlegroups.org
Maintainer: Malthe Borch
Maintainer-email: mborch@gmail.com
License: BSD
Keywords: pyramid templates
Platform: UNKNOWN
Classifier: Development Status :: 4 - Beta
Classifier: Environment :: Web Environment
Classifier: Intended Audience :: Developers
Classifier: License :: OSI Approved :: Zope Public License
Classifier: Programming Language :: Python
Classifier: Programming Language :: Python :: 3 :: Only
Classifier: Natural Language :: English
Classifier: Operating System :: OS Independent
Classifier: Topic :: Internet :: WWW/HTTP
Classifier: Framework :: BFG
Requires-Python: >=3.7
Requires-Dist: setuptools
Requires-Dist: Chameleon (>=2.7)
Requires-Dist: zope.interface
Requires-Dist: pyramid (>=1.5)
Provides-Extra: development
Requires-Dist: manuel ; extra == 'development'
Requires-Dist: coverage ; extra == 'development'
Requires-Dist: nose2 ; extra == 'development'
Requires-Dist: pyramid-zcml (>=0.9.2) ; extra == 'development'
Requires-Dist: zope.testing (>3.8.7) ; extra == 'development'
Requires-Dist: zope.component (>3.9.2) ; extra == 'development'
Requires-Dist: Sphinx ; extra == 'development'
Requires-Dist: docutils ; extra == 'development'
Requires-Dist: repoze.sphinx.autointerface ; extra == 'development'
Requires-Dist: MacFSEvents ; (sys_platform == "darwin") and extra == 'development'
Requires-Dist: pyinotify ; (sys_platform == "linux") and extra == 'development'
Provides-Extra: docs
Requires-Dist: Sphinx ; extra == 'docs'
Requires-Dist: docutils ; extra == 'docs'
Requires-Dist: repoze.sphinx.autointerface ; extra == 'docs'
Provides-Extra: testing
Requires-Dist: manuel ; extra == 'testing'
Requires-Dist: coverage ; extra == 'testing'
Requires-Dist: nose2 ; extra == 'testing'
Requires-Dist: pyramid-zcml (>=0.9.2) ; extra == 'testing'
Requires-Dist: zope.testing (>3.8.7) ; extra == 'testing'
Requires-Dist: zope.component (>3.9.2) ; extra == 'testing'
Requires-Dist: MacFSEvents ; (sys_platform == "darwin") and extra == 'testing'
Requires-Dist: pyinotify ; (sys_platform == "linux") and extra == 'testing'
